hopt/__init__.py
hopt/hopt.py
hopt/keras.py
hopt/randoms.py
hopt/utils.py
hopt-0.2.1.dist-info/LICENSE
hopt-0.2.1.dist-info/METADATA
hopt-0.2.1.dist-info/WHEEL
hopt-0.2.1.dist-info/top_level.txt
hopt-0.2.1.dist-info/RECORD
